{
  "global": {},
  "SemanticColor/Mode 1": {
    "color": {
      "test": {
        "value": "#ffffff",
        "type": "color",
        "parent": "SemanticColor/Mode 1",
        "description": ""
      }
    }
  },
  "PrimitiveColor/light": {
    "grey": {
      "0": {
        "value": "#ffffff",
        "type": "color",
        "parent": "PrimitiveColor/light",
        "description": ""
      },
      "50": {
        "value": "#f0f1f2",
        "type": "color",
        "parent": "PrimitiveColor/light",
        "description": ""
      },
      "100": {
        "value": "#e1e3e6",
        "type": "color",
        "parent": "PrimitiveColor/light",
        "description": ""
      },
      "150": {
        "value": "#d3d5d9",
        "type": "color",
        "parent": "PrimitiveColor/light",
        "description": ""
      },
      "200": {
        "value": "#c4c7cc",
        "type": "color",
        "parent": "PrimitiveColor/light",
        "description": ""
      },
      "300": {
        "value": "#a6aab3",
        "type": "color",
        "parent": "PrimitiveColor/light",
        "description": ""
      },
      "400": {
        "value": "#898e99",
        "type": "color",
        "parent": "PrimitiveColor/light",
        "description": ""
      },
      "500": {
        "value": "#6b7280",
        "type": "color",
        "parent": "PrimitiveColor/light",
        "description": ""
      },
      "600": {
        "value": "#565b66",
        "type": "color",
        "parent": "PrimitiveColor/light",
        "description": ""
      },
      "700": {
        "value": "#40444d",
        "type": "color",
        "parent": "PrimitiveColor/light",
        "description": ""
      },
      "800": {
        "value": "#2b2e33",
        "type": "color",
        "parent": "PrimitiveColor/light",
        "description": ""
      },
      "850": {
        "value": "#202226",
        "type": "color",
        "parent": "PrimitiveColor/light",
        "description": ""
      },
      "900": {
        "value": "#15171a",
        "type": "color",
        "parent": "PrimitiveColor/light",
        "description": ""
      },
      "950": {
        "value": "#0b0b0d",
        "type": "color",
        "parent": "PrimitiveColor/light",
        "description": ""
      },
      "1000": {
        "value": "#000000",
        "type": "color",
        "parent": "PrimitiveColor/light",
        "description": ""
      }
    },
    "red": {
      "0": {
        "value": "#fccdcd",
        "type": "color",
        "parent": "PrimitiveColor/light",
        "description": ""
      },
      "50": {
        "value": "#fbbaba",
        "type": "color",
        "parent": "PrimitiveColor/light",
        "description": ""
      },
      "100": {
        "value": "#f9a7a7",
        "type": "color",
        "parent": "PrimitiveColor/light",
        "description": ""
      },
      "150": {
        "value": "#f89494",
        "type": "color",
        "parent": "PrimitiveColor/light",
        "description": ""
      },
      "200": {
        "value": "#f78181",
        "type": "color",
        "parent": "PrimitiveColor/light",
        "description": ""
      },
      "300": {
        "value": "#f45a5a",
        "type": "color",
        "parent": "PrimitiveColor/light",
        "description": ""
      },
      "400": {
        "value": "#f23434",
        "type": "color",
        "parent": "PrimitiveColor/light",
        "description": ""
      },
      "500": {
        "value": "#ef0e0e",
        "type": "color",
        "parent": "PrimitiveColor/light",
        "description": ""
      },
      "600": {
        "value": "#c80c0c",
        "type": "color",
        "parent": "PrimitiveColor/light",
        "description": ""
      },
      "700": {
        "value": "#a20a0a",
        "type": "color",
        "parent": "PrimitiveColor/light",
        "description": ""
      },
      "800": {
        "value": "#7b0707",
        "type": "color",
        "parent": "PrimitiveColor/light",
        "description": ""
      },
      "850": {
        "value": "#680606",
        "type": "color",
        "parent": "PrimitiveColor/light",
        "description": ""
      },
      "900": {
        "value": "#550505",
        "type": "color",
        "parent": "PrimitiveColor/light",
        "description": ""
      }
    },
    "green": {
      "0": {
        "value": "#d1ffd6",
        "type": "color",
        "parent": "PrimitiveColor/light",
        "description": ""
      },
      "50": {
        "value": "#bcf6c3",
        "type": "color",
        "parent": "PrimitiveColor/light",
        "description": ""
      },
      "100": {
        "value": "#a7edaf",
        "type": "color",
        "parent": "PrimitiveColor/light",
        "description": ""
      },
      "150": {
        "value": "#93e59c",
        "type": "color",
        "parent": "PrimitiveColor/light",
        "description": ""
      },
      "200": {
        "value": "#7edc88",
        "type": "color",
        "parent": "PrimitiveColor/light",
        "description": ""
      },
      "300": {
        "value": "#54ca62",
        "type": "color",
        "parent": "PrimitiveColor/light",
        "description": ""
      },
      "400": {
        "value": "#2bb93b",
        "type": "color",
        "parent": "PrimitiveColor/light",
        "description": ""
      },
      "500": {
        "value": "#01a714",
        "type": "color",
        "parent": "PrimitiveColor/light",
        "description": ""
      },
      "600": {
        "value": "#018610",
        "type": "color",
        "parent": "PrimitiveColor/light",
        "description": ""
      },
      "700": {
        "value": "#01640c",
        "type": "color",
        "parent": "PrimitiveColor/light",
        "description": ""
      },
      "800": {
        "value": "#004308",
        "type": "color",
        "parent": "PrimitiveColor/light",
        "description": ""
      },
      "850": {
        "value": "#003206",
        "type": "color",
        "parent": "PrimitiveColor/light",
        "description": ""
      },
      "900": {
        "value": "#002104",
        "type": "color",
        "parent": "PrimitiveColor/light",
        "description": ""
      }
    },
    "blue": {
      "0": {
        "value": "#cfe2fc",
        "type": "color",
        "parent": "PrimitiveColor/light",
        "description": ""
      },
      "50": {
        "value": "#bcd7fb",
        "type": "color",
        "parent": "PrimitiveColor/light",
        "description": ""
      },
      "100": {
        "value": "#a8cbfa",
        "type": "color",
        "parent": "PrimitiveColor/light",
        "description": ""
      },
      "150": {
        "value": "#95c0f9",
        "type": "color",
        "parent": "PrimitiveColor/light",
        "description": ""
      },
      "200": {
        "value": "#82b4f8",
        "type": "color",
        "parent": "PrimitiveColor/light",
        "description": ""
      },
      "300": {
        "value": "#5b9ef5",
        "type": "color",
        "parent": "PrimitiveColor/light",
        "description": ""
      },
      "400": {
        "value": "#3587f3",
        "type": "color",
        "parent": "PrimitiveColor/light",
        "description": ""
      },
      "500": {
        "value": "#0e70f1",
        "type": "color",
        "parent": "PrimitiveColor/light",
        "description": ""
      },
      "600": {
        "value": "#0c5eca",
        "type": "color",
        "parent": "PrimitiveColor/light",
        "description": ""
      },
      "700": {
        "value": "#0a4ca4",
        "type": "color",
        "parent": "PrimitiveColor/light",
        "description": ""
      },
      "800": {
        "value": "#073a7d",
        "type": "color",
        "parent": "PrimitiveColor/light",
        "description": ""
      },
      "850": {
        "value": "#06316a",
        "type": "color",
        "parent": "PrimitiveColor/light",
        "description": ""
      },
      "900": {
        "value": "#052857",
        "type": "color",
        "parent": "PrimitiveColor/light",
        "description": ""
      }
    },
    "yellow": {
      "0": {
        "value": "#ffffff",
        "type": "color",
        "parent": "PrimitiveColor/light",
        "description": ""
      },
      "50": {
        "value": "#fdf7e6",
        "type": "color",
        "parent": "PrimitiveColor/light",
        "description": ""
      },
      "100": {
        "value": "#fbf0ce",
        "type": "color",
        "parent": "PrimitiveColor/light",
        "description": ""
      },
      "150": {
        "value": "#f9e8b5",
        "type": "color",
        "parent": "PrimitiveColor/light",
        "description": ""
      },
      "200": {
        "value": "#f7e19c",
        "type": "color",
        "parent": "PrimitiveColor/light",
        "description": ""
      },
      "300": {
        "value": "#f2d16b",
        "type": "color",
        "parent": "PrimitiveColor/light",
        "description": ""
      },
      "400": {
        "value": "#eec239",
        "type": "color",
        "parent": "PrimitiveColor/light",
        "description": ""
      },
      "500": {
        "value": "#eab308",
        "type": "color",
        "parent": "PrimitiveColor/light",
        "description": ""
      },
      "600": {
        "value": "#bb8f06",
        "type": "color",
        "parent": "PrimitiveColor/light",
        "description": ""
      },
      "700": {
        "value": "#8c6b05",
        "type": "color",
        "parent": "PrimitiveColor/light",
        "description": ""
      },
      "800": {
        "value": "#5e4803",
        "type": "color",
        "parent": "PrimitiveColor/light",
        "description": ""
      },
      "850": {
        "value": "#463602",
        "type": "color",
        "parent": "PrimitiveColor/light",
        "description": ""
      },
      "900": {
        "value": "#2f2402",
        "type": "color",
        "parent": "PrimitiveColor/light",
        "description": ""
      }
    }
  },
  "PrimitiveColor/dark": {
    "grey": {
      "0": {
        "value": "#000000",
        "type": "color",
        "parent": "PrimitiveColor/dark",
        "description": ""
      },
      "50": {
        "value": "#0b0b0d",
        "type": "color",
        "parent": "PrimitiveColor/dark",
        "description": ""
      },
      "100": {
        "value": "#15171a",
        "type": "color",
        "parent": "PrimitiveColor/dark",
        "description": ""
      },
      "150": {
        "value": "#202226",
        "type": "color",
        "parent": "PrimitiveColor/dark",
        "description": ""
      },
      "200": {
        "value": "#2b2e33",
        "type": "color",
        "parent": "PrimitiveColor/dark",
        "description": ""
      },
      "300": {
        "value": "#40444d",
        "type": "color",
        "parent": "PrimitiveColor/dark",
        "description": ""
      },
      "400": {
        "value": "#565b66",
        "type": "color",
        "parent": "PrimitiveColor/dark",
        "description": ""
      },
      "500": {
        "value": "#6b7280",
        "type": "color",
        "parent": "PrimitiveColor/dark",
        "description": ""
      },
      "600": {
        "value": "#898e99",
        "type": "color",
        "parent": "PrimitiveColor/dark",
        "description": ""
      },
      "700": {
        "value": "#a6aab3",
        "type": "color",
        "parent": "PrimitiveColor/dark",
        "description": ""
      },
      "800": {
        "value": "#c4c7cc",
        "type": "color",
        "parent": "PrimitiveColor/dark",
        "description": ""
      },
      "850": {
        "value": "#d3d5d9",
        "type": "color",
        "parent": "PrimitiveColor/dark",
        "description": ""
      },
      "900": {
        "value": "#e1e3e6",
        "type": "color",
        "parent": "PrimitiveColor/dark",
        "description": ""
      },
      "950": {
        "value": "#f0f1f2",
        "type": "color",
        "parent": "PrimitiveColor/dark",
        "description": ""
      },
      "1000": {
        "value": "#ffffff",
        "type": "color",
        "parent": "PrimitiveColor/dark",
        "description": ""
      }
    },
    "red": {
      "0": {
        "value": "#550505",
        "type": "color",
        "parent": "PrimitiveColor/dark",
        "description": ""
      },
      "50": {
        "value": "#680606",
        "type": "color",
        "parent": "PrimitiveColor/dark",
        "description": ""
      },
      "100": {
        "value": "#7b0707",
        "type": "color",
        "parent": "PrimitiveColor/dark",
        "description": ""
      },
      "150": {
        "value": "#a20a0a",
        "type": "color",
        "parent": "PrimitiveColor/dark",
        "description": ""
      },
      "200": {
        "value": "#c80c0c",
        "type": "color",
        "parent": "PrimitiveColor/dark",
        "description": ""
      },
      "300": {
        "value": "#ef0e0e",
        "type": "color",
        "parent": "PrimitiveColor/dark",
        "description": ""
      },
      "400": {
        "value": "#f23434",
        "type": "color",
        "parent": "PrimitiveColor/dark",
        "description": ""
      },
      "500": {
        "value": "#f45a5a",
        "type": "color",
        "parent": "PrimitiveColor/dark",
        "description": ""
      },
      "600": {
        "value": "#f78181",
        "type": "color",
        "parent": "PrimitiveColor/dark",
        "description": ""
      },
      "700": {
        "value": "#f89494",
        "type": "color",
        "parent": "PrimitiveColor/dark",
        "description": ""
      },
      "800": {
        "value": "#f9a7a7",
        "type": "color",
        "parent": "PrimitiveColor/dark",
        "description": ""
      },
      "850": {
        "value": "#fbbaba",
        "type": "color",
        "parent": "PrimitiveColor/dark",
        "description": ""
      },
      "900": {
        "value": "#fccdcd",
        "type": "color",
        "parent": "PrimitiveColor/dark",
        "description": ""
      }
    },
    "green": {
      "0": {
        "value": "#002104",
        "type": "color",
        "parent": "PrimitiveColor/dark",
        "description": ""
      },
      "50": {
        "value": "#003206",
        "type": "color",
        "parent": "PrimitiveColor/dark",
        "description": ""
      },
      "100": {
        "value": "#004308",
        "type": "color",
        "parent": "PrimitiveColor/dark",
        "description": ""
      },
      "150": {
        "value": "#01640c",
        "type": "color",
        "parent": "PrimitiveColor/dark",
        "description": ""
      },
      "200": {
        "value": "#018610",
        "type": "color",
        "parent": "PrimitiveColor/dark",
        "description": ""
      },
      "300": {
        "value": "#01a714",
        "type": "color",
        "parent": "PrimitiveColor/dark",
        "description": ""
      },
      "400": {
        "value": "#2bb93b",
        "type": "color",
        "parent": "PrimitiveColor/dark",
        "description": ""
      },
      "500": {
        "value": "#54ca62",
        "type": "color",
        "parent": "PrimitiveColor/dark",
        "description": ""
      },
      "600": {
        "value": "#7edc88",
        "type": "color",
        "parent": "PrimitiveColor/dark",
        "description": ""
      },
      "700": {
        "value": "#93e59c",
        "type": "color",
        "parent": "PrimitiveColor/dark",
        "description": ""
      },
      "800": {
        "value": "#a7edaf",
        "type": "color",
        "parent": "PrimitiveColor/dark",
        "description": ""
      },
      "850": {
        "value": "#bcf6c3",
        "type": "color",
        "parent": "PrimitiveColor/dark",
        "description": ""
      },
      "900": {
        "value": "#d1ffd6",
        "type": "color",
        "parent": "PrimitiveColor/dark",
        "description": ""
      }
    },
    "blue": {
      "0": {
        "value": "#052857",
        "type": "color",
        "parent": "PrimitiveColor/dark",
        "description": ""
      },
      "50": {
        "value": "#06316a",
        "type": "color",
        "parent": "PrimitiveColor/dark",
        "description": ""
      },
      "100": {
        "value": "#073a7d",
        "type": "color",
        "parent": "PrimitiveColor/dark",
        "description": ""
      },
      "150": {
        "value": "#0a4ca4",
        "type": "color",
        "parent": "PrimitiveColor/dark",
        "description": ""
      },
      "200": {
        "value": "#0c5eca",
        "type": "color",
        "parent": "PrimitiveColor/dark",
        "description": ""
      },
      "300": {
        "value": "#0e70f1",
        "type": "color",
        "parent": "PrimitiveColor/dark",
        "description": ""
      },
      "400": {
        "value": "#3587f3",
        "type": "color",
        "parent": "PrimitiveColor/dark",
        "description": ""
      },
      "500": {
        "value": "#5b9ef5",
        "type": "color",
        "parent": "PrimitiveColor/dark",
        "description": ""
      },
      "600": {
        "value": "#82b4f8",
        "type": "color",
        "parent": "PrimitiveColor/dark",
        "description": ""
      },
      "700": {
        "value": "#95c0f9",
        "type": "color",
        "parent": "PrimitiveColor/dark",
        "description": ""
      },
      "800": {
        "value": "#a8cbfa",
        "type": "color",
        "parent": "PrimitiveColor/dark",
        "description": ""
      },
      "850": {
        "value": "#bcd7fb",
        "type": "color",
        "parent": "PrimitiveColor/dark",
        "description": ""
      },
      "900": {
        "value": "#cfe2fc",
        "type": "color",
        "parent": "PrimitiveColor/dark",
        "description": ""
      }
    },
    "yellow": {
      "0": {
        "value": "#2f2402",
        "type": "color",
        "parent": "PrimitiveColor/dark",
        "description": ""
      },
      "50": {
        "value": "#463602",
        "type": "color",
        "parent": "PrimitiveColor/dark",
        "description": ""
      },
      "100": {
        "value": "#5e4803",
        "type": "color",
        "parent": "PrimitiveColor/dark",
        "description": ""
      },
      "150": {
        "value": "#8c6b05",
        "type": "color",
        "parent": "PrimitiveColor/dark",
        "description": ""
      },
      "200": {
        "value": "#bb8f06",
        "type": "color",
        "parent": "PrimitiveColor/dark",
        "description": ""
      },
      "300": {
        "value": "#eab308",
        "type": "color",
        "parent": "PrimitiveColor/dark",
        "description": ""
      },
      "400": {
        "value": "#eec239",
        "type": "color",
        "parent": "PrimitiveColor/dark",
        "description": ""
      },
      "500": {
        "value": "#f2d16b",
        "type": "color",
        "parent": "PrimitiveColor/dark",
        "description": ""
      },
      "600": {
        "value": "#f7e19c",
        "type": "color",
        "parent": "PrimitiveColor/dark",
        "description": ""
      },
      "700": {
        "value": "#f9e8b5",
        "type": "color",
        "parent": "PrimitiveColor/dark",
        "description": ""
      },
      "800": {
        "value": "#fbf0ce",
        "type": "color",
        "parent": "PrimitiveColor/dark",
        "description": ""
      },
      "850": {
        "value": "#fdf7e6",
        "type": "color",
        "parent": "PrimitiveColor/dark",
        "description": ""
      },
      "900": {
        "value": "#ffffff",
        "type": "color",
        "parent": "PrimitiveColor/dark",
        "description": ""
      }
    }
  },
  "ThemeColor/light": {
    "teal": {
      "0": {
        "value": "#d1faf5",
        "type": "color",
        "parent": "ThemeColor/light",
        "description": ""
      },
      "50": {
        "value": "#bef3ed",
        "type": "color",
        "parent": "ThemeColor/light",
        "description": ""
      },
      "100": {
        "value": "#abede5",
        "type": "color",
        "parent": "ThemeColor/light",
        "description": ""
      },
      "150": {
        "value": "#98e6dd",
        "type": "color",
        "parent": "ThemeColor/light",
        "description": ""
      },
      "200": {
        "value": "#85e0d5",
        "type": "color",
        "parent": "ThemeColor/light",
        "description": ""
      },
      "300": {
        "value": "#60d2c6",
        "type": "color",
        "parent": "ThemeColor/light",
        "description": ""
      },
      "400": {
        "value": "#3ac5b6",
        "type": "color",
        "parent": "ThemeColor/light",
        "description": ""
      },
      "500": {
        "value": "#14b8a6",
        "type": "color",
        "parent": "ThemeColor/light",
        "description": ""
      },
      "600": {
        "value": "#109385",
        "type": "color",
        "parent": "ThemeColor/light",
        "description": ""
      },
      "700": {
        "value": "#0c6e64",
        "type": "color",
        "parent": "ThemeColor/light",
        "description": ""
      },
      "800": {
        "value": "#084a42",
        "type": "color",
        "parent": "ThemeColor/light",
        "description": ""
      },
      "850": {
        "value": "#063732",
        "type": "color",
        "parent": "ThemeColor/light",
        "description": ""
      },
      "900": {
        "value": "#042521",
        "type": "color",
        "parent": "ThemeColor/light",
        "description": ""
      }
    },
    "green": {
      "0": {
        "value": "#ebfbf1",
        "type": "color",
        "parent": "ThemeColor/light",
        "description": ""
      },
      "50": {
        "value": "#d7f6e2",
        "type": "color",
        "parent": "ThemeColor/light",
        "description": ""
      },
      "100": {
        "value": "#c3f0d4",
        "type": "color",
        "parent": "ThemeColor/light",
        "description": ""
      },
      "150": {
        "value": "#afebc5",
        "type": "color",
        "parent": "ThemeColor/light",
        "description": ""
      },
      "200": {
        "value": "#9be5b6",
        "type": "color",
        "parent": "ThemeColor/light",
        "description": ""
      },
      "300": {
        "value": "#72db99",
        "type": "color",
        "parent": "ThemeColor/light",
        "description": ""
      },
      "400": {
        "value": "#4ad07b",
        "type": "color",
        "parent": "ThemeColor/light",
        "description": ""
      },
      "500": {
        "value": "#22c55e",
        "type": "color",
        "parent": "ThemeColor/light",
        "description": ""
      },
      "600": {
        "value": "#1b9e4b",
        "type": "color",
        "parent": "ThemeColor/light",
        "description": ""
      },
      "700": {
        "value": "#147638",
        "type": "color",
        "parent": "ThemeColor/light",
        "description": ""
      },
      "800": {
        "value": "#0e4f26",
        "type": "color",
        "parent": "ThemeColor/light",
        "description": ""
      },
      "850": {
        "value": "#0a3b1c",
        "type": "color",
        "parent": "ThemeColor/light",
        "description": ""
      },
      "900": {
        "value": "#072713",
        "type": "color",
        "parent": "ThemeColor/light",
        "description": ""
      }
    },
    "sky": {
      "0": {
        "value": "#f7fcff",
        "type": "color",
        "parent": "ThemeColor/light",
        "description": ""
      },
      "50": {
        "value": "#e0f3fd",
        "type": "color",
        "parent": "ThemeColor/light",
        "description": ""
      },
      "100": {
        "value": "#c8ebfb",
        "type": "color",
        "parent": "ThemeColor/light",
        "description": ""
      },
      "150": {
        "value": "#b1e2f8",
        "type": "color",
        "parent": "ThemeColor/light",
        "description": ""
      },
      "200": {
        "value": "#9ad9f6",
        "type": "color",
        "parent": "ThemeColor/light",
        "description": ""
      },
      "300": {
        "value": "#6bc8f2",
        "type": "color",
        "parent": "ThemeColor/light",
        "description": ""
      },
      "400": {
        "value": "#3db6ed",
        "type": "color",
        "parent": "ThemeColor/light",
        "description": ""
      },
      "500": {
        "value": "#0ea5e9",
        "type": "color",
        "parent": "ThemeColor/light",
        "description": ""
      },
      "600": {
        "value": "#0b84ba",
        "type": "color",
        "parent": "ThemeColor/light",
        "description": ""
      },
      "700": {
        "value": "#08638c",
        "type": "color",
        "parent": "ThemeColor/light",
        "description": ""
      },
      "800": {
        "value": "#06425d",
        "type": "color",
        "parent": "ThemeColor/light",
        "description": ""
      },
      "850": {
        "value": "#043246",
        "type": "color",
        "parent": "ThemeColor/light",
        "description": ""
      },
      "900": {
        "value": "#03212f",
        "type": "color",
        "parent": "ThemeColor/light",
        "description": ""
      }
    }
  },
  "ThemeColor/dark": {
    "teal": {
      "0": {
        "value": "#042521",
        "type": "color",
        "parent": "ThemeColor/dark",
        "description": ""
      },
      "50": {
        "value": "#063732",
        "type": "color",
        "parent": "ThemeColor/dark",
        "description": ""
      },
      "100": {
        "value": "#084a42",
        "type": "color",
        "parent": "ThemeColor/dark",
        "description": ""
      },
      "150": {
        "value": "#0c6e64",
        "type": "color",
        "parent": "ThemeColor/dark",
        "description": ""
      },
      "200": {
        "value": "#109385",
        "type": "color",
        "parent": "ThemeColor/dark",
        "description": ""
      },
      "300": {
        "value": "#14b8a6",
        "type": "color",
        "parent": "ThemeColor/dark",
        "description": ""
      },
      "400": {
        "value": "#3ac5b6",
        "type": "color",
        "parent": "ThemeColor/dark",
        "description": ""
      },
      "500": {
        "value": "#60d2c6",
        "type": "color",
        "parent": "ThemeColor/dark",
        "description": ""
      },
      "600": {
        "value": "#85e0d5",
        "type": "color",
        "parent": "ThemeColor/dark",
        "description": ""
      },
      "700": {
        "value": "#98e6dd",
        "type": "color",
        "parent": "ThemeColor/dark",
        "description": ""
      },
      "800": {
        "value": "#abede5",
        "type": "color",
        "parent": "ThemeColor/dark",
        "description": ""
      },
      "850": {
        "value": "#bef3ed",
        "type": "color",
        "parent": "ThemeColor/dark",
        "description": ""
      },
      "900": {
        "value": "#d1faf5",
        "type": "color",
        "parent": "ThemeColor/dark",
        "description": ""
      }
    },
    "green": {
      "0": {
        "value": "#072713",
        "type": "color",
        "parent": "ThemeColor/dark",
        "description": ""
      },
      "50": {
        "value": "#0a3b1c",
        "type": "color",
        "parent": "ThemeColor/dark",
        "description": ""
      },
      "100": {
        "value": "#0e4f26",
        "type": "color",
        "parent": "ThemeColor/dark",
        "description": ""
      },
      "150": {
        "value": "#147638",
        "type": "color",
        "parent": "ThemeColor/dark",
        "description": ""
      },
      "200": {
        "value": "#1b9e4b",
        "type": "color",
        "parent": "ThemeColor/dark",
        "description": ""
      },
      "300": {
        "value": "#22c55e",
        "type": "color",
        "parent": "ThemeColor/dark",
        "description": ""
      },
      "400": {
        "value": "#4ad07b",
        "type": "color",
        "parent": "ThemeColor/dark",
        "description": ""
      },
      "500": {
        "value": "#72db99",
        "type": "color",
        "parent": "ThemeColor/dark",
        "description": ""
      },
      "600": {
        "value": "#9be5b6",
        "type": "color",
        "parent": "ThemeColor/dark",
        "description": ""
      },
      "700": {
        "value": "#afebc5",
        "type": "color",
        "parent": "ThemeColor/dark",
        "description": ""
      },
      "800": {
        "value": "#c3f0d4",
        "type": "color",
        "parent": "ThemeColor/dark",
        "description": ""
      },
      "850": {
        "value": "#d7f6e2",
        "type": "color",
        "parent": "ThemeColor/dark",
        "description": ""
      },
      "900": {
        "value": "#ebfbf1",
        "type": "color",
        "parent": "ThemeColor/dark",
        "description": ""
      }
    },
    "sky": {
      "0": {
        "value": "#03212f",
        "type": "color",
        "parent": "ThemeColor/dark",
        "description": ""
      },
      "50": {
        "value": "#043246",
        "type": "color",
        "parent": "ThemeColor/dark",
        "description": ""
      },
      "100": {
        "value": "#06425d",
        "type": "color",
        "parent": "ThemeColor/dark",
        "description": ""
      },
      "150": {
        "value": "#08638c",
        "type": "color",
        "parent": "ThemeColor/dark",
        "description": ""
      },
      "200": {
        "value": "#0b84ba",
        "type": "color",
        "parent": "ThemeColor/dark",
        "description": ""
      },
      "300": {
        "value": "#0ea5e9",
        "type": "color",
        "parent": "ThemeColor/dark",
        "description": ""
      },
      "400": {
        "value": "#3db6ed",
        "type": "color",
        "parent": "ThemeColor/dark",
        "description": ""
      },
      "500": {
        "value": "#6bc8f2",
        "type": "color",
        "parent": "ThemeColor/dark",
        "description": ""
      },
      "600": {
        "value": "#9ad9f6",
        "type": "color",
        "parent": "ThemeColor/dark",
        "description": ""
      },
      "700": {
        "value": "#b1e2f8",
        "type": "color",
        "parent": "ThemeColor/dark",
        "description": ""
      },
      "800": {
        "value": "#c8ebfb",
        "type": "color",
        "parent": "ThemeColor/dark",
        "description": ""
      },
      "850": {
        "value": "#e0f3fd",
        "type": "color",
        "parent": "ThemeColor/dark",
        "description": ""
      },
      "900": {
        "value": "#f7fcff",
        "type": "color",
        "parent": "ThemeColor/dark",
        "description": ""
      }
    }
  },
  "$themes": [],
  "$metadata": {
    "tokenSetOrder": [
      "global",
      "SemanticColor/Mode 1",
      "PrimitiveColor/light",
      "PrimitiveColor/dark",
      "ThemeColor/light",
      "ThemeColor/dark"
    ]
  }
}